{
  "AuthorID": "pptrsha1",
  "AuthorURL": "http://www.healingwell.com/community/profile.aspx?f=14&m=3354755&p=192512",
  "EmotionInfo": {
    "EmotionKeywords": [
      "great",
      "touched",
      "close",
      "caring",
      "sure",
      "lost",
      "pained",
      "pained",
      "pained",
      "tearful",
      "pained"
    ],
    "Emotions": {
      "AFRAID": "0",
      "ALIVE": "0",
      "ANGRY": "0",
      "CONFUSED": "0.5",
      "DEPRESSED": "0",
      "GOOD": "0",
      "HAPPY": "0.5",
      "HELPLESS": "0",
      "HURT": "1",
      "INDIFFERENT": "0",
      "INTERESTED": "0",
      "LOVE": "1.5",
      "OPEN": "0",
      "POSITIVE": "0",
      "SAD": "1.5",
      "STRONG": "0.5"
    }
  },
  "GleasonInfo": {},
  "NExperiencePosts": 2,
  "NPosts": 2,
  "PSAInfo": {},
  "PostTypeInfo": {
    "-1 Month PostTypeInfo": {
      "NAdvice": 0,
      "NExperience": 0,
      "NTotal": 0,
      "PAdvice": 0,
      "PExperience": 0
    },
    "-2 Month PostTypeInfo": {
      "NAdvice": 0,
      "NExperience": 0,
      "NTotal": 0,
      "PAdvice": 0,
      "PExperience": 0
    },
    "-3 Month PostTypeInfo": {
      "NAdvice": 0,
      "NExperience": 0,
      "NTotal": 0,
      "PAdvice": 0,
      "PExperience": 0
    },
    "10th Month PostTypeInfo": {
      "NAdvice": 0,
      "NExperience": 0,
      "NTotal": 0,
      "PAdvice": 0,
      "PExperience": 0
    },
    "11th Month PostTypeInfo": {
      "NAdvice": 0,
      "NExperience": 0,
      "NTotal": 0,
      "PAdvice": 0,
      "PExperience": 0
    },
    "12th Month PostTypeInfo": {
      "NAdvice": 0,
      "NExperience": 0,
      "NTotal": 0,
      "PAdvice": 0,
      "PExperience": 0
    },
    "13th Month PostTypeInfo": {
      "NAdvice": 0,
      "NExperience": 0,
      "NTotal": 0,
      "PAdvice": 0,
      "PExperience": 0
    },
    "18th Month PostTypeInfo": {
      "NAdvice": 0,
      "NExperience": 0,
      "NTotal": 0,
      "PAdvice": 0,
      "PExperience": 0
    },
    "1st Month PostTypeInfo": {
      "NAdvice": 0,
      "NExperience": 2,
      "NTotal": 2,
      "PAdvice": 0,
      "PExperience": 1
    },
    "24th Month PostTypeInfo": {
      "NAdvice": 0,
      "NExperience": 0,
      "NTotal": 0,
      "PAdvice": 0,
      "PExperience": 0
    },
    "2nd Month PostTypeInfo": {
      "NAdvice": 0,
      "NExperience": 0,
      "NTotal": 0,
      "PAdvice": 0,
      "PExperience": 0
    },
    "3rd Month PostTypeInfo": {
      "NAdvice": 0,
      "NExperience": 0,
      "NTotal": 0,
      "PAdvice": 0,
      "PExperience": 0
    },
    "4th Month PostTypeInfo": {
      "NAdvice": 0,
      "NExperience": 0,
      "NTotal": 0,
      "PAdvice": 0,
      "PExperience": 0
    },
    "5th Month PostTypeInfo": {
      "NAdvice": 0,
      "NExperience": 0,
      "NTotal": 0,
      "PAdvice": 0,
      "PExperience": 0
    },
    "6th Month PostTypeInfo": {
      "NAdvice": 0,
      "NExperience": 0,
      "NTotal": 0,
      "PAdvice": 0,
      "PExperience": 0
    },
    "7th Month PostTypeInfo": {
      "NAdvice": 0,
      "NExperience": 0,
      "NTotal": 0,
      "PAdvice": 0,
      "PExperience": 0
    },
    "8th Month PostTypeInfo": {
      "NAdvice": 0,
      "NExperience": 0,
      "NTotal": 0,
      "PAdvice": 0,
      "PExperience": 0
    },
    "9th Month PostTypeInfo": {
      "NAdvice": 0,
      "NExperience": 0,
      "NTotal": 0,
      "PAdvice": 0,
      "PExperience": 0
    }
  },
  "Posts": [
    {
      "AuthorID": "pptrsha1",
      "AuthorURL": "http://www.healingwell.com/community/profile.aspx?f=14&m=3354755&p=192512",
      "Content": " hi all I am mostly in chronic pain site. \nI let years go by since my last pap test AGAIN\nin 2009 I had a mammogram done. my gyn dr said it was 50 % chance of being cancer so I had another done and they said it was cysts. I had to get mammograms every 6 months I did it for the first year and I never went back. I had a hysterectomy in 1998 I still have my ovaries.\nI started bleeding like I am having a period lightly......dark reddish brown, just enough to have to wear a pad or ruin my undergarments and britches. I have had nausea and sweating spells for more than a month now and I have been out of menopause since 2008\nmy doc died last year\n I read it could be dry tissue related from age????? wth? I am 53 yrs old. on the other hand I haven't had a sex life since 2001. my husband had a genetic disorder that he had to have extensive surgery and it caused severe nerve damage, result E.D. with no cure then he started stroking out he lost the speech center in his brain and is still learning to communicate\nlast night I woke from a sound sleep with burning pain across my left breast and It sent me through the roof when I touched the area close to my armpit and in a line across mid breast. \nI used to joke that I was so small breasted that a mammogram for me would be a chest xray. now I am not joking. I got on the phone this morning and called a new gyn and made an appt. for APRIL 1ST! GREAT A JOKE DAY! in my mind I am going over and over what I have to do to make sure my husband is taken care of and doesn't have to deal with if I die and now I cant sleep. I always take everything to the extreme ",
      "Demographics": {
        "AgeInfo": [
          {
            "Confidence": 1,
            "Phrase": "gyn dr said it was 50 % chance of being cancer",
            "Relation": "unknown",
            "Tense": "past",
            "Value": 50
          },
          {
            "Confidence": 1,
            "Phrase": "<Z> <Z> <Z> I am 53 yrs old  on the other",
            "Relation": "unknown",
            "Tense": "present",
            "Value": 53
          }
        ],
        "GenderInfo": {
          "MedicalTermBasedGender": {
            "FemaleMedicalTerms": [
              "hysterectomy",
              "mammogram",
              "menopause",
              "breast"
            ],
            "MaleMedicalTerms": []
          },
          "NounBasedGender": {
            "MainSubject": "I",
            "NarrationType": "first-person",
            "NarratorGender": "female",
            "PatientGender": "female"
          }
        }
      },
      "MessageIndex": 0,
      "PostDate": "13/03/2015",
      "ThreadURL": "http://www.healingwell.com/community/default.aspx?f=14&m=3354755",
      "Title": "time to deal with it"
    },
    {
      "AuthorID": "pptrsha1",
      "AuthorURL": "http://www.healingwell.com/community/profile.aspx?f=14&m=110474&p=192512",
      "Content": " pat 53 sandusky ohio\nI used to say my pain was an 8 or a 10. then I found out it can get worse. muscle spasms caused hypolordosis 2 failed rotator cuff surgeries OA DDD stenosis 2 slipped discs cervical and lumbar impingment extrusion/protrusion endplate edema hypertrophic flavum annular tears vasculitus ,cyroglobulinemea and all the * that comes with it raynauds etc carpal tunnel adenomyosis hysterectyomy ",
      "Demographics": {
        "AgeInfo": [],
        "GenderInfo": {
          "MedicalTermBasedGender": {
            "FemaleMedicalTerms": [],
            "MaleMedicalTerms": []
          },
          "NounBasedGender": {
            "MainSubject": "I",
            "NarrationType": "first-person",
            "NarratorGender": "unknown",
            "PatientGender": "unknown"
          }
        }
      },
      "MessageIndex": 174,
      "PostDate": "13/03/2015",
      "ThreadURL": "http://www.healingwell.com/community/default.aspx?f=14&m=110474",
      "Title": "ROLL CALL name, age, state and any other info to share"
    }
  ],
  "ProfileDemographics": {
    "Age": {
      "Confidence": 1,
      "Phrase": "<Z> <Z> <Z> I am 53 yrs old  on the other",
      "Relation": "unknown",
      "Tense": "present",
      "Value": 53
    },
    "Gender": {
      "Confidence": 1,
      "Gender": "female",
      "NarrationType": "first-person"
    }
  },
  "SideEffectTypeInfo": {
    "SideEffectType": [
      "Bladder Irritation",
      "Bleeding"
    ],
    "SideEffectTypeKeywords": [
      "burning",
      "bleeding"
    ]
  },
  "TreatmentDecision": {
    "DoctorRecommended": {
      "Age": 0,
      "Best Cancer Control": 0,
      "Bowel Symptoms": 0,
      "Doctor Skill": 0,
      "Erectile dysfunction": 0,
      "Financial": 0,
      "GP Mentioned": 0,
      "Less Invasive": 0,
      "Medical Indication": 0,
      "Nerve": 0,
      "Radiologist": 0,
      "Recovery Time": 0,
      "Source": 0,
      "Surgeon": 0,
      "Urinary incontinence": 0,
      "Value": 0
    },
    "PatientDecided": {
      "Age": 0,
      "Best Cancer Control": 0,
      "Bowel Symptoms": 0,
      "Doctor Skill": 0,
      "Erectile dysfunction": 0,
      "Financial": 0,
      "GP Mentioned": 0,
      "Less Invasive": 0,
      "Medical Indication": 0,
      "Nerve": 0,
      "Radiologist": 0,
      "Recovery Time": 0,
      "Source": 0,
      "Surgeon": 0,
      "Urinary incontinence": 0,
      "Value": 0
    }
  },
  "TreatmentTimelineInfo": {
    "-1 Month Emotions": {
      "EmotionKeywords": [],
      "Emotions": {
        "AFRAID": 0,
        "ALIVE": 0,
        "ANGRY": 0,
        "CONFUSED": 0,
        "DEPRESSED": 0,
        "GOOD": 0,
        "HAPPY": 0,
        "HELPLESS": 0,
        "HURT": 0,
        "INDIFFERENT": 0,
        "INTERESTED": 0,
        "LOVE": 0,
        "OPEN": 0,
        "POSITIVE": 0,
        "SAD": 0,
        "STRONG": 0
      }
    },
    "-1 Month SideEffects": {
      "SideEffectType": [],
      "SideEffectTypeKeywords": []
    },
    "-2 Month Emotions": {
      "EmotionKeywords": [],
      "Emotions": {
        "AFRAID": 0,
        "ALIVE": 0,
        "ANGRY": 0,
        "CONFUSED": 0,
        "DEPRESSED": 0,
        "GOOD": 0,
        "HAPPY": 0,
        "HELPLESS": 0,
        "HURT": 0,
        "INDIFFERENT": 0,
        "INTERESTED": 0,
        "LOVE": 0,
        "OPEN": 0,
        "POSITIVE": 0,
        "SAD": 0,
        "STRONG": 0
      }
    },
    "-2 Month SideEffects": {
      "SideEffectType": [],
      "SideEffectTypeKeywords": []
    },
    "-3 Month Emotions": {
      "EmotionKeywords": [],
      "Emotions": {
        "AFRAID": 0,
        "ALIVE": 0,
        "ANGRY": 0,
        "CONFUSED": 0,
        "DEPRESSED": 0,
        "GOOD": 0,
        "HAPPY": 0,
        "HELPLESS": 0,
        "HURT": 0,
        "INDIFFERENT": 0,
        "INTERESTED": 0,
        "LOVE": 0,
        "OPEN": 0,
        "POSITIVE": 0,
        "SAD": 0,
        "STRONG": 0
      }
    },
    "-3 Month SideEffects": {
      "SideEffectType": [],
      "SideEffectTypeKeywords": []
    },
    "10th Month Emotions": {
      "EmotionKeywords": [],
      "Emotions": {
        "AFRAID": 0,
        "ALIVE": 0,
        "ANGRY": 0,
        "CONFUSED": 0,
        "DEPRESSED": 0,
        "GOOD": 0,
        "HAPPY": 0,
        "HELPLESS": 0,
        "HURT": 0,
        "INDIFFERENT": 0,
        "INTERESTED": 0,
        "LOVE": 0,
        "OPEN": 0,
        "POSITIVE": 0,
        "SAD": 0,
        "STRONG": 0
      }
    },
    "10th Month SideEffects": {
      "SideEffectType": [],
      "SideEffectTypeKeywords": []
    },
    "11th Month Emotions": {
      "EmotionKeywords": [],
      "Emotions": {
        "AFRAID": 0,
        "ALIVE": 0,
        "ANGRY": 0,
        "CONFUSED": 0,
        "DEPRESSED": 0,
        "GOOD": 0,
        "HAPPY": 0,
        "HELPLESS": 0,
        "HURT": 0,
        "INDIFFERENT": 0,
        "INTERESTED": 0,
        "LOVE": 0,
        "OPEN": 0,
        "POSITIVE": 0,
        "SAD": 0,
        "STRONG": 0
      }
    },
    "11th Month SideEffects": {
      "SideEffectType": [],
      "SideEffectTypeKeywords": []
    },
    "12th Month Emotions": {
      "EmotionKeywords": [],
      "Emotions": {
        "AFRAID": 0,
        "ALIVE": 0,
        "ANGRY": 0,
        "CONFUSED": 0,
        "DEPRESSED": 0,
        "GOOD": 0,
        "HAPPY": 0,
        "HELPLESS": 0,
        "HURT": 0,
        "INDIFFERENT": 0,
        "INTERESTED": 0,
        "LOVE": 0,
        "OPEN": 0,
        "POSITIVE": 0,
        "SAD": 0,
        "STRONG": 0
      }
    },
    "12th Month SideEffects": {
      "SideEffectType": [],
      "SideEffectTypeKeywords": []
    },
    "13th Month Emotions": {
      "EmotionKeywords": [],
      "Emotions": {
        "AFRAID": 0,
        "ALIVE": 0,
        "ANGRY": 0,
        "CONFUSED": 0,
        "DEPRESSED": 0,
        "GOOD": 0,
        "HAPPY": 0,
        "HELPLESS": 0,
        "HURT": 0,
        "INDIFFERENT": 0,
        "INTERESTED": 0,
        "LOVE": 0,
        "OPEN": 0,
        "POSITIVE": 0,
        "SAD": 0,
        "STRONG": 0
      }
    },
    "13th Month SideEffects": {
      "SideEffectType": [],
      "SideEffectTypeKeywords": []
    },
    "18th Month Emotions": {
      "EmotionKeywords": [],
      "Emotions": {
        "AFRAID": 0,
        "ALIVE": 0,
        "ANGRY": 0,
        "CONFUSED": 0,
        "DEPRESSED": 0,
        "GOOD": 0,
        "HAPPY": 0,
        "HELPLESS": 0,
        "HURT": 0,
        "INDIFFERENT": 0,
        "INTERESTED": 0,
        "LOVE": 0,
        "OPEN": 0,
        "POSITIVE": 0,
        "SAD": 0,
        "STRONG": 0
      }
    },
    "18th Month SideEffects": {
      "SideEffectType": [],
      "SideEffectTypeKeywords": []
    },
    "1st Month Emotions": {
      "EmotionKeywords": [
        "great",
        "touched",
        "close",
        "caring",
        "sure",
        "lost",
        "pained",
        "pained",
        "pained",
        "tearful",
        "pained"
      ],
      "Emotions": {
        "AFRAID": "0",
        "ALIVE": "0",
        "ANGRY": "0",
        "CONFUSED": "0.5",
        "DEPRESSED": "0",
        "GOOD": "0",
        "HAPPY": "0.5",
        "HELPLESS": "0",
        "HURT": "1",
        "INDIFFERENT": "0",
        "INTERESTED": "0",
        "LOVE": "1.5",
        "OPEN": "0",
        "POSITIVE": "0",
        "SAD": "1.5",
        "STRONG": "0.5"
      }
    },
    "1st Month SideEffects": {
      "SideEffectType": [
        "Bladder Irritation",
        "Bleeding"
      ],
      "SideEffectTypeKeywords": [
        "burning",
        "bleeding"
      ]
    },
    "24th Month Emotions": {
      "EmotionKeywords": [],
      "Emotions": {
        "AFRAID": 0,
        "ALIVE": 0,
        "ANGRY": 0,
        "CONFUSED": 0,
        "DEPRESSED": 0,
        "GOOD": 0,
        "HAPPY": 0,
        "HELPLESS": 0,
        "HURT": 0,
        "INDIFFERENT": 0,
        "INTERESTED": 0,
        "LOVE": 0,
        "OPEN": 0,
        "POSITIVE": 0,
        "SAD": 0,
        "STRONG": 0
      }
    },
    "24th Month SideEffects": {
      "SideEffectType": [],
      "SideEffectTypeKeywords": []
    },
    "2nd Month Emotions": {
      "EmotionKeywords": [],
      "Emotions": {
        "AFRAID": 0,
        "ALIVE": 0,
        "ANGRY": 0,
        "CONFUSED": 0,
        "DEPRESSED": 0,
        "GOOD": 0,
        "HAPPY": 0,
        "HELPLESS": 0,
        "HURT": 0,
        "INDIFFERENT": 0,
        "INTERESTED": 0,
        "LOVE": 0,
        "OPEN": 0,
        "POSITIVE": 0,
        "SAD": 0,
        "STRONG": 0
      }
    },
    "2nd Month SideEffects": {
      "SideEffectType": [],
      "SideEffectTypeKeywords": []
    },
    "3rd Month Emotions": {
      "EmotionKeywords": [],
      "Emotions": {
        "AFRAID": 0,
        "ALIVE": 0,
        "ANGRY": 0,
        "CONFUSED": 0,
        "DEPRESSED": 0,
        "GOOD": 0,
        "HAPPY": 0,
        "HELPLESS": 0,
        "HURT": 0,
        "INDIFFERENT": 0,
        "INTERESTED": 0,
        "LOVE": 0,
        "OPEN": 0,
        "POSITIVE": 0,
        "SAD": 0,
        "STRONG": 0
      }
    },
    "3rd Month SideEffects": {
      "SideEffectType": [],
      "SideEffectTypeKeywords": []
    },
    "4th Month Emotions": {
      "EmotionKeywords": [],
      "Emotions": {
        "AFRAID": 0,
        "ALIVE": 0,
        "ANGRY": 0,
        "CONFUSED": 0,
        "DEPRESSED": 0,
        "GOOD": 0,
        "HAPPY": 0,
        "HELPLESS": 0,
        "HURT": 0,
        "INDIFFERENT": 0,
        "INTERESTED": 0,
        "LOVE": 0,
        "OPEN": 0,
        "POSITIVE": 0,
        "SAD": 0,
        "STRONG": 0
      }
    },
    "4th Month SideEffects": {
      "SideEffectType": [],
      "SideEffectTypeKeywords": []
    },
    "5th Month Emotions": {
      "EmotionKeywords": [],
      "Emotions": {
        "AFRAID": 0,
        "ALIVE": 0,
        "ANGRY": 0,
        "CONFUSED": 0,
        "DEPRESSED": 0,
        "GOOD": 0,
        "HAPPY": 0,
        "HELPLESS": 0,
        "HURT": 0,
        "INDIFFERENT": 0,
        "INTERESTED": 0,
        "LOVE": 0,
        "OPEN": 0,
        "POSITIVE": 0,
        "SAD": 0,
        "STRONG": 0
      }
    },
    "5th Month SideEffects": {
      "SideEffectType": [],
      "SideEffectTypeKeywords": []
    },
    "6th Month Emotions": {
      "EmotionKeywords": [],
      "Emotions": {
        "AFRAID": 0,
        "ALIVE": 0,
        "ANGRY": 0,
        "CONFUSED": 0,
        "DEPRESSED": 0,
        "GOOD": 0,
        "HAPPY": 0,
        "HELPLESS": 0,
        "HURT": 0,
        "INDIFFERENT": 0,
        "INTERESTED": 0,
        "LOVE": 0,
        "OPEN": 0,
        "POSITIVE": 0,
        "SAD": 0,
        "STRONG": 0
      }
    },
    "6th Month SideEffects": {
      "SideEffectType": [],
      "SideEffectTypeKeywords": []
    },
    "7th Month Emotions": {
      "EmotionKeywords": [],
      "Emotions": {
        "AFRAID": 0,
        "ALIVE": 0,
        "ANGRY": 0,
        "CONFUSED": 0,
        "DEPRESSED": 0,
        "GOOD": 0,
        "HAPPY": 0,
        "HELPLESS": 0,
        "HURT": 0,
        "INDIFFERENT": 0,
        "INTERESTED": 0,
        "LOVE": 0,
        "OPEN": 0,
        "POSITIVE": 0,
        "SAD": 0,
        "STRONG": 0
      }
    },
    "7th Month SideEffects": {
      "SideEffectType": [],
      "SideEffectTypeKeywords": []
    },
    "8th Month Emotions": {
      "EmotionKeywords": [],
      "Emotions": {
        "AFRAID": 0,
        "ALIVE": 0,
        "ANGRY": 0,
        "CONFUSED": 0,
        "DEPRESSED": 0,
        "GOOD": 0,
        "HAPPY": 0,
        "HELPLESS": 0,
        "HURT": 0,
        "INDIFFERENT": 0,
        "INTERESTED": 0,
        "LOVE": 0,
        "OPEN": 0,
        "POSITIVE": 0,
        "SAD": 0,
        "STRONG": 0
      }
    },
    "8th Month SideEffects": {
      "SideEffectType": [],
      "SideEffectTypeKeywords": []
    },
    "9th Month Emotions": {
      "EmotionKeywords": [],
      "Emotions": {
        "AFRAID": 0,
        "ALIVE": 0,
        "ANGRY": 0,
        "CONFUSED": 0,
        "DEPRESSED": 0,
        "GOOD": 0,
        "HAPPY": 0,
        "HELPLESS": 0,
        "HURT": 0,
        "INDIFFERENT": 0,
        "INTERESTED": 0,
        "LOVE": 0,
        "OPEN": 0,
        "POSITIVE": 0,
        "SAD": 0,
        "STRONG": 0
      }
    },
    "9th Month SideEffects": {
      "SideEffectType": [],
      "SideEffectTypeKeywords": []
    },
    "DateOfTreatment": "13/03/2015",
    "TreatmentType": "Surgery",
    "Verified": 1
  },
  "TreatmentTypeInfo": {
    "TreatmentMentions": ["Surgery"],
    "TreatmentType": "Surgery",
    "TreatmentTypeKeywords": ["surgery"]
  },
  "WordCount": 411
}