{
  "AuthorID": "tori1950",
  "AuthorURL": "https://www.healthboards.comhttps://www.healthboards.com/tori1950",
  "Posts": [{
    "AuthorID": "tori1950",
    "AuthorURL": "https://www.healthboards.comhttps://www.healthboards.com/tori1950",
    "Content": "Had a mammogram monday and my doctor said it showed microcalcifications in the left breast. I am going in tomorrow for more \"views\" and maybe an ultrasound. I'm really scared.",
    "MessageIndex": 0,
    "PostDate": "04/06/2008",
    "ThreadURL": "https://www.healthboards.com/boards/cancer-breast/607249-had-mammogram-monday-showed-microcalcifications.html",
    "Title": "Had a mammogram monday and showed microcalcifications"
  }]
}