{
  "AuthorID": "catriona789\u2026",
  "AuthorURL": "https://community.breastcancer.orghttps://community.breastcancer.org/member/287106/profile",
  "Posts": [{
    "AuthorID": "catriona789\u2026",
    "AuthorURL": "https://community.breastcancer.orghttps://community.breastcancer.org/member/287106/profile",
    "Content": "Mar 28, 2019 01:13AM catriona7899 wrote:",
    "MessageIndex": 156,
    "PostDate": "28/03/2019",
    "ThreadURL": "https://community.breastcancer.org/forum/83/topics/855477",
    "Title": "Anxiety MTwoman godisone"
  }]
}