{
  "AuthorID": "Cindyterrazas",
  "AuthorURL": "https://community.breastcancer.orghttps://community.breastcancer.org/member/204482/profile",
  "Posts": [{
    "AuthorID": "Cindyterrazas",
    "AuthorURL": "https://community.breastcancer.orghttps://community.breastcancer.org/member/204482/profile",
    "Content": "Cindyterrazas wrote: should I be worried, if I had a abnormal mammogram?  The doctor indicates the a spot in my right breast has grown in size . Any and all he is appreciated Log in to post a reply",
    "MessageIndex": 0,
    "PostDate": "27/08/2014",
    "ThreadURL": "https://community.breastcancer.org/forum/83/topics/824031",
    "Title": "Worried Cindyterrazas Moderators"
  }]
}