{
  "AuthorID": "hockeymommy\u2026",
  "AuthorURL": "https://community.breastcancer.orghttps://community.breastcancer.org/member/182984/profile",
  "Posts": [{
    "AuthorID": "hockeymommy\u2026",
    "AuthorURL": "https://community.breastcancer.orghttps://community.breastcancer.org/member/182984/profile",
    "Content": "Jul 6, 2013 09:47PM hockeymommy wrote: Traii, I hope you are doing well.....big hugs....",
    "MessageIndex": 4242,
    "PostDate": "06/07/2013",
    "ThreadURL": "https://community.breastcancer.org/forum/5/topics/792706",
    "Title": "In shock bennymuffins websister"
  }]
}