{
  "AuthorID": "jeannie85",
  "AuthorURL": "https://community.breastcancer.orghttps://community.breastcancer.org/member/51102/profile",
  "Posts": [
    {
      "AuthorID": "jeannie85",
      "AuthorURL": "https://community.breastcancer.orghttps://community.breastcancer.org/member/51102/profile",
      "Content": "Jul 18, 2007 04:46PM jeannie85 wrote: Congratulations!!",
      "MessageIndex": 5,
      "PostDate": "18/07/2007",
      "ThreadURL": "https://community.breastcancer.org/forum/83/topics/656586",
      "Title": "Pass the confetti here too! tashaw6 KristinaK"
    },
    {
      "AuthorID": "jeannie85",
      "AuthorURL": "https://community.breastcancer.orghttps://community.breastcancer.org/member/51102/profile",
      "Content": "Jun 2, 2007 08:26PM jeannie85 wrote:",
      "MessageIndex": 15,
      "PostDate": "02/06/2007",
      "ThreadURL": "https://community.breastcancer.org/forum/83/topics/623901",
      "Title": "So Afraid Patti7920 lady4law"
    }
  ]
}