{
  "AuthorID": "Kiranoel",
  "AuthorURL": "https://community.breastcancer.orghttps://community.breastcancer.org/member/184742/profile",
  "Posts": [{
    "AuthorID": "Kiranoel",
    "AuthorURL": "https://community.breastcancer.orghttps://community.breastcancer.org/member/184742/profile",
    "Content": "Jul 23, 2013 07:00PM Kiranoel wrote: I do not have cancer, but have had shooting paints, joint pain, swelling feet and neuropathy. My feet and hands were very numb. After six weeks of jin shin my tingling is gone and my feet are waking up. My pain is also gone and burning is minimal. Jin shin is a god send!",
    "MessageIndex": 6,
    "PostDate": "23/07/2013",
    "ThreadURL": "https://community.breastcancer.org/forum/8/topics/753655",
    "Title": "Jin Shin Jyutsu (accupressure) stopped my neuropathy radiant Kiranoel"
  }]
}