{
  "AuthorID": "lanekoeslin\u2026",
  "AuthorURL": "https://community.breastcancer.orghttps://community.breastcancer.org/member/100370/profile",
  "Posts": [{
    "AuthorID": "lanekoeslin\u2026",
    "AuthorURL": "https://community.breastcancer.orghttps://community.breastcancer.org/member/100370/profile",
    "Content": "Apr 14, 2010 12:23PM lanekoeslin wrote: 71",
    "MessageIndex": 468,
    "PostDate": "14/04/2010",
    "ThreadURL": "https://community.breastcancer.org/forum/8/topics/729146",
    "Title": "Poll - How old were you when dx with BC Times3 Minetta57"
  }]
}