{
  "AuthorID": "Tazchurch kelly68563",
  "AuthorURL": "https://patient.infohttps://patient.info/forums/profiles/tazchurch-381560",
  "Posts": [{
    "AuthorID": "Tazchurch kelly68563",
    "AuthorURL": "https://patient.infohttps://patient.info/forums/profiles/tazchurch-381560",
    "Content": "This is evidentally worrying you, ask for a refferal to a breast clinic, it is your legal right to ask for referal and your GP cannot refuse (be it about this or anything else, just be clear what you want). Breast cancer care helpine page, good to talk to about worries and an amazing range of leaflets:- \"Free Helpline 0808 800 6000 Our regular Helpline hours are: Monday-Friday, 9am-5pm, Saturday, 10am-2pm Please note: We are closed on English bank holidays Our free, confidential Helpline is here to answer any questions about breast cancer or breast health. Calls are answered by nurses and trained staff with experience of breast cancer. Whatever your concern, you can be confident we\u2019ll understand the issues you might be facing, and that the information you\u2019ll receive is clear and up to date. We will also let you know where else you can go for further support and information.\" Report",
    "MessageIndex": 1,
    "PostDate": "09/12/2014",
    "ThreadURL": "https://patient.info/forums/discuss/please-read-worried-sick--324792",
    "Title": "Please read. Worried sick!!!"
  }]
}